cpp.py
cpppy-1.0.0.dist-info/WHEEL
cpppy-1.0.0.dist-info/METADATA
cpppy-1.0.0.dist-info/RECORD
