Metadata-Version: 2.1
Name: cpppy
Version: 1.0.0
Summary: Implementing C++ Semantics in Python
Home-page: https://github.com/tmr232/cpppy
License: MIT
Author: Tamir Bahar
Requires-Python: >=3.7,<4.0
Classifier: License :: OSI Approved :: MIT License
Classifier: Programming Language :: Python :: 3
Classifier: Programming Language :: Python :: 3.7
Classifier: Programming Language :: Python :: 3.8
Classifier: Programming Language :: Python :: 3.9
Project-URL: Repository, https://github.com/tmr232/cpppy
